README.md
setup.py
lerMicrodados/__init__.py
lerMicrodados/lerMicrodados.py
lerMicrodados/test_lerMicrodados.py
lerMicrodados.egg-info/PKG-INFO
lerMicrodados.egg-info/SOURCES.txt
lerMicrodados.egg-info/dependency_links.txt
lerMicrodados.egg-info/requires.txt
lerMicrodados.egg-info/top_level.txt