Metadata-Version: 2.1
Name: lerMicrodados
Version: 0.6
Summary: Este pacote contém funções para leitura de microdados da POF e PNAD.
Home-page: https://github.com/otavio-s-s/lerMicrodados
Author: Otávio Silveira
Author-email: otavios.s@hotmail.com
License: MIT License
Keywords: Microdados,PNAD,POF
Platform: UNKNOWN
